dvb/__init__.py
dvb/dvb.py
dvb-1.2.dist-info/DESCRIPTION.rst
dvb-1.2.dist-info/METADATA
dvb-1.2.dist-info/RECORD
dvb-1.2.dist-info/WHEEL
dvb-1.2.dist-info/metadata.json
dvb-1.2.dist-info/top_level.txt
