Metadata-Version: 2.0
Name: dvb
Version: 1.2
Summary: query Dresden's public transport system for current bus- and tramstop data in python
Home-page: https://github.com/kiliankoe/dvbpy
Author: kiliankoe
Author-email: me@kilian.io
License: MIT
Keywords: dvb vvo tram bus public transport dresden
Platform: UNKNOWN
Classifier: Development Status :: 4 - Beta
Classifier: License :: OSI Approved :: MIT License
Classifier: Programming Language :: Python :: 3
Classifier: Programming Language :: Python :: 3.3
Classifier: Programming Language :: Python :: 3.4
Classifier: Programming Language :: Python :: 3.5
Requires-Dist: pyproj
Requires-Dist: requests (==2.5.0)
